odoo/addons/l10n_th_withholding_tax_cert/README.rst
odoo/addons/l10n_th_withholding_tax_cert/__init__.py
odoo/addons/l10n_th_withholding_tax_cert/__manifest__.py
odoo/addons/l10n_th_withholding_tax_cert/i18n/l10n_th_withholding_tax_cert.pot
odoo/addons/l10n_th_withholding_tax_cert/i18n/th.po
odoo/addons/l10n_th_withholding_tax_cert/models/__init__.py
odoo/addons/l10n_th_withholding_tax_cert/models/account_move.py
odoo/addons/l10n_th_withholding_tax_cert/models/account_payment.py
odoo/addons/l10n_th_withholding_tax_cert/models/withholding_tax_cert.py
odoo/addons/l10n_th_withholding_tax_cert/readme/CONFIGURE.rst
odoo/addons/l10n_th_withholding_tax_cert/readme/CONTRIBUTORS.rst
odoo/addons/l10n_th_withholding_tax_cert/readme/DESCRIPTION.rst
odoo/addons/l10n_th_withholding_tax_cert/readme/USAGE.rst
odoo/addons/l10n_th_withholding_tax_cert/security/account_security.xml
odoo/addons/l10n_th_withholding_tax_cert/security/ir.model.access.csv
odoo/addons/l10n_th_withholding_tax_cert/static/description/icon.png
odoo/addons/l10n_th_withholding_tax_cert/static/description/index.html
odoo/addons/l10n_th_withholding_tax_cert/tests/__init__.py
odoo/addons/l10n_th_withholding_tax_cert/tests/test_wt_cert.py
odoo/addons/l10n_th_withholding_tax_cert/views/account_move_view.xml
odoo/addons/l10n_th_withholding_tax_cert/views/account_payment_view.xml
odoo/addons/l10n_th_withholding_tax_cert/views/withholding_tax_cert.xml
odoo/addons/l10n_th_withholding_tax_cert/wizard/__init__.py
odoo/addons/l10n_th_withholding_tax_cert/wizard/create_withholding_tax_cert.py
odoo/addons/l10n_th_withholding_tax_cert/wizard/create_withholding_tax_cert.xml
odoo14_addon_l10n_th_withholding_tax_cert-14.0.1.0.1.dist-info/METADATA
odoo14_addon_l10n_th_withholding_tax_cert-14.0.1.0.1.dist-info/WHEEL
odoo14_addon_l10n_th_withholding_tax_cert-14.0.1.0.1.dist-info/top_level.txt
odoo14_addon_l10n_th_withholding_tax_cert-14.0.1.0.1.dist-info/RECORD
