Metadata-Version: 2.1
Name: odoo14-addon-l10n-th-withholding-tax-cert
Version: 14.0.1.0.1
Summary: Thai Localization - Withholding Tax Certificate
Home-page: https://github.com/OCA/l10n-thailand
Author: Ecosoft, Odoo Community Association (OCA)
Author-email: support@odoo-community.org
License: AGPL-3
Platform: UNKNOWN
Classifier: Programming Language :: Python
Classifier: Framework :: Odoo
Classifier: License :: OSI Approved :: GNU Affero General Public License v3
Classifier: Development Status :: 4 - Beta
Requires-Python: >=3.6
Requires-Dist: odoo14-addon-l10n-th-withholding-tax
Requires-Dist: odoo (<14.1dev,>=14.0a)
